Workbook

Sheet Assumptions
A1: Input | B1: Value | C1: Unit | D1: Source / note
A2: Contacts per month | B2: 45000 | C2: contacts | D2: Brief
A3: Share in scope (disputes, fees, cards) | B3: 0.6 | C3: % | D3: Brief (our ticket sample: 56%)
A4: Contact growth per year | B4: 0.15 | C4: % | D4: Brief
A5: Agents | B5: 120 | C5: agents | D5: Brief
A6: Fully loaded cost per agent per month | B6: 20000 | C6: EGP | D6: ASSUMPTION - asked the instructor; test 15k-30k
A7: Average handle time, all contacts | B7: 8.87 | C7: min | D7: Our synthetic tickets (200)
A8: Average handle time, in-scope contacts | B8: 9.75 | C8: min | D8: Our synthetic tickets
A9: Minutes saved per assisted contact (base) | B9: 2 | C9: min | D9: ASSUMPTION; BofA EricaAssist ~1 min/call is the floor (research/competitors.md)
A10: Share of in-scope contacts where agents use the copilot | B10: 0.8 | C10: % | D10: ASSUMPTION
A11: Copilot drafts per contact | B11: 1.3 | C11: drafts | D11: ASSUMPTION (some retries and follow-ups)
A12: Model cost per draft | B12: 0.0344 | C12: USD | D12: MEASURED in our eval run (Claude Opus 5.5 incl. guard model)
A13: EGP per USD | B13: 56.12 | C13: EGP | D13: CBE rate 29 Oct 2026 (research/regulation.md)
... A17: Phase 2 starts in month | B17: 7 | C17: month | D17: Roadmap

Sheet Model
A1: Output | B1: Year 1 (today's volume) | C1: Year 2 (+15% volume) | D1: How it's calculated
A2: In-scope contacts per month | B2: =Assumptions!$B$2*Assumptions!$B$3 | C2: =Assumptions!$B$2*(1+Assumptions!$B$4)*Assumptions!$B$3 | D2: contacts x scope share
A3: Agent minutes per month (no copilot) | B3: =Assumptions!$B$2*Assumptions!$B$7 | C3: =Assumptions!$B$2*(1+Assumptions!$B$4)*Assumptions!$B$7 | D3: contacts x AHT
A4: Minutes per agent per month (capacity) | B4: =Assumptions!$B$2*Assumptions!$B$7/Assumptions!$B$5 | C4: =C4 | D4: today's minutes / 120 agents
A5: Agents needed without copilot | B5: =B3/B4 | C5: =C3/C4 | D5: minutes / capacity
A6: PHASE 1 - agent copilot
A7: Minutes saved per month | B7: =B2*Assumptions!$B$10*Assumptions!$B$9 | C7: =C2*Assumptions!$B$10*Assumptions!$B$9 | D7: in-scope x adoption x minutes saved
A8: Agent capacity freed (FTE) | B8: =B7/B4 | C8: =C7/C4 | D8: minutes saved / capacity
A9: Value of freed capacity per month (EGP) | B9: =B8*Assumptions!$B$6 | C9: =C8*Assumptions!$B$6 | D9: FTE x cost per agent
A10: Hires avoided next year | C10: =MIN(C8,C5-Assumptions!$B$5) | D10: growth absorbed: freed FTE, capped at the hires growth needs
A11: Model cost per month (EGP) | B11: =B2*Assumptions!$B$10*Assumptions!$B$11*Assumptions!$B$12*Assumptions!$B$13 | C11: =C2*Assumptions!$B$10*Assumptions!$B$11*Assumptions!$B$12*Assumptions!$B$13 | D11: drafts x measured cost
A12: Cost per assisted contact (EGP) | B12: =B11/(B2*Assumptions!$B$10) | C12: =C11/(C2*Assumptions!$B$10) | D12: model cost / assisted contacts
A13: Agent cost per contact today (EGP) | B13: =Assumptions!$B$5*Assumptions!$B$6/Assumptions!$B$2 | D13: agent payroll / contacts
A14: PHASE 2 - customer-facing (from month 7)
A15: Contacts resolved in the app per month | B15: =B2*Assumptions!$B$16 | C15: =C2*Assumptions!$B$16 | D15: in-scope x deflection
A16: Agent capacity freed (FTE) | B16: =B15*Assumptions!$B$8/B4 | C16: =C15*Assumptions!$B$8/C4 | D16: deflected x in-scope AHT / capacity
A17: Value per month (EGP) | B17: =B16*Assumptions!$B$6 | C17: =C16*Assumptions!$B$6 | D17: FTE x cost per agent
A18: YEAR 1 TOTALS
A19: Value (EGP) | B19: =12*B9+(13-Assumptions!$B$17)*B17 | D19: 12 months Phase 1 + Phase 2 from start month
A20: Cost (EGP) | B20: =Assumptions!$B$15+12*(Assumptions!$B$14+B11) | D20: build + hosting + model
A21: Net (EGP) | B21: =B19-B20 | D21: value - cost
A22: Payback (months) | B22: =Assumptions!$B$15/((B19-12*(Assumptions!$B$14+B11))/12) | D22: build / average monthly net

Sheet Sensitivity
A1: Value of freed capacity per month (EGP), Year 1 - minutes saved per contact vs cost per agent
A2: Minutes saved \ EGP per agent | B2: 15000 | C2: 20000 | D2: 25000 | E2: 30000
A3: 1 | B3: =Model!$B$2*Assumptions!$B$10*1.0/Model!$B$4*15000 | C3: =Model!$B$2*Assumptions!$B$10*1.0/Model!$B$4*20000 | D3: =Model!$B$2*Assumptions!$B$10*1.0/Model!$B$4*25000 | E3: =Model!$B$2*Assumptions!$B$10*1.0/Model!$B$4*30000
A4: 1.5 | B4: =Model!$B$2*Assumptions!$B$10*1.5/Model!$B$4*15000 | C4: =Model!$B$2*Assumptions!$B$10*1.5/Model!$B$4*20000 | D4: =Model!$B$2*Assumptions!$B$10*1.5/Model!$B$4*25000 | E4: =Model!$B$2*Assumptions!$B$10*1.5/Model!$B$4*30000
A5: 2 | B5: =Model!$B$2*Assumptions!$B$10*2.0/Model!$B$4*15000 | C5: =Model!$B$2*Assumptions!$B$10*2.0/Model!$B$4*20000 | D5: =Model!$B$2*Assumptions!$B$10*2.0/Model!$B$4*25000 | E5: =Model!$B$2*Assumptions!$B$10*2.0/Model!$B$4*30000
A6: 2.5 | B6: =Model!$B$2*Assumptions!$B$10*2.5/Model!$B$4*15000 | C6: =Model!$B$2*Assumptions!$B$10*2.5/Model!$B$4*20000 | D6: =Model!$B$2*Assumptions!$B$10*2.5/Model!$B$4*25000 | E6: =Model!$B$2*Assumptions!$B$10*2.5/Model!$B$4*30000
A7: 3 | B7: =Model!$B$2*Assumptions!$B$10*3.0/Model!$B$4*15000 | C7: =Model!$B$2*Assumptions!$B$10*3.0/Model!$B$4*20000 | D7: =Model!$B$2*Assumptions!$B$10*3.0/Model!$B$4*25000 | E7: =Model!$B$2*Assumptions!$B$10*3.0/Model!$B$4*30000

Sheet Budget ask
A1: Internal budget request (instructor: frame as an internal team asking for budget) | B1: EGP | D1: Basis
A2: Year 1 budget: build + 12 months of running | B2: =Assumptions!$B$15+12*(Assumptions!$B$14+Model!B11) | D2: Assumptions + Model sheets
A3: of which one-off build | B3: =Assumptions!$B$15 | D3: 4 people x 3 months
A4: of which running cost per month | B4: =Assumptions!$B$14+Model!B11 | D4: in-country hosting + measured model cost
A5: All-in cost per assisted contact | B5: =(Assumptions!$B$14+Model!B11)/(Model!B2*Assumptions!$B$10) | D5: running cost / assisted contacts
A6: Agent cost per contact today | B6: =Model!B13 | D6: for comparison
A7: Year 1 value | B7: =Model!B19 | D7: freed agent capacity, Phase 1 + Phase 2
A8: Year 1 net | B8: =Model!B21 | D8: value - budget
A10: Build vs buy: what the same 120 seats would cost from a vendor | B10: EGP / month | D10: Why we still build
A11: Intercom Copilot, $29 / agent / month | B11: =29*Assumptions!$B$13*Assumptions!$B$5 | D11: No Egyptian Arabic or Franco-Arabic; hosted abroad (bank secrecy blocks customer data)
A12: Zendesk Copilot, $50 / agent / month | B12: =50*Assumptions!$B$13*Assumptions!$B$5 | D12: Same; also needs Zendesk as the helpdesk
A13: Microsoft D365 Contact Center, $110 / user / month | B13: =110*Assumptions!$B$13*Assumptions!$B$5 | D13: Full platform replacement, not just a copilot
A14: Phase 2 benchmark: Intercom Fin, $0.99 / resolution | B14: =0.99*Assumptions!$B$13*Model!C15 | D14: Customer-facing; offshore hosting
A15: Source: research/competitors.md, list prices checked 30 Oct 2026, USD 1 = EGP 56.12
